simple_requirements_export/__init__.py
simple_requirements_export/command.py
simple_requirements_export/plugin.py
poetry_plugin_simple_requirements_export-0.1.2.dist-info/WHEEL
poetry_plugin_simple_requirements_export-0.1.2.dist-info/entry_points.txt
poetry_plugin_simple_requirements_export-0.1.2.dist-info/METADATA
poetry_plugin_simple_requirements_export-0.1.2.dist-info/RECORD
