Metadata-Version: 2.1
Name: poetry-plugin-simple-requirements-export
Version: 0.1.2
Summary: A different way to export your poetry requirements as a requirements.txt file
License: MIT
Author: Antonio Feregrino
Author-email: antonio.feregrino@gmail.com
Requires-Python: >=3.8,<4.0
Classifier: License :: OSI Approved :: MIT License
Classifier: Programming Language :: Python :: 3
Classifier: Programming Language :: Python :: 3.8
Classifier: Programming Language :: Python :: 3.9
Classifier: Programming Language :: Python :: 3.10
Classifier: Programming Language :: Python :: 3.11
Requires-Dist: poetry (>=1.3.2,<2.0.0)
Requires-Dist: tomli (>=2.0.1,<3.0.0)
